logyca/__init__.py
logyca/dependencies/__init__.py
logyca/dependencies/api_key_simple_auth.py
logyca/dependencies/oauth_token.py
logyca/schemas/__init__.py
logyca/schemas/input/__init__.py
logyca/schemas/input/api_key.py
logyca/schemas/input/claimsdto.py
logyca/schemas/input/jwt.py
logyca/schemas/input/oauth_token.py
logyca/schemas/output/__init__.py
logyca/schemas/output/apIresultdto.py
logyca/schemas/output/apifilterexceptiondto.py
logyca/schemas/output/healthdto.py
logyca/schemas/output/httpexceptiondto.py
logyca/schemas/output/tokensdto.py
logyca/utils/__init__.py
logyca/utils/constants/__init__.py
logyca/utils/constants/app.py
logyca/utils/constants/healthenum.py
logyca/utils/constants/logycastatusenum.py
logyca/utils/constants/messages.py
logyca/utils/handlers/__init__.py
logyca/utils/handlers/exception_handlers.py
logyca/utils/handlers/logger.py
logyca/utils/handlers/singleton.py
logyca/utils/helpers/__init__.py
logyca/utils/helpers/datetimehelpers.py
logyca/utils/helpers/parse_functions.py
logyca/utils/helpers/stringshelpers.py
logyca-0.1.19.dist-info/LICENSE.txt
logyca-0.1.19.dist-info/METADATA
logyca-0.1.19.dist-info/WHEEL
logyca-0.1.19.dist-info/top_level.txt
logyca-0.1.19.dist-info/RECORD
