Metadata-Version: 2.1
Name: logyca
Version: 0.1.19
Summary: This package name is reserved by LOGYCA company
Home-page: https://github.com/logyca/python-libraries/tree/main/logyca
Author: Jaime Andres Cardona Carrillo
Author-email: jacardona@outlook.com
License: MIT License
Keywords: api result,result dto,result scheme
Classifier: Development Status :: 4 - Beta
Classifier: Environment :: Web Environment
Classifier: Framework :: Pydantic :: 1
Classifier: Framework :: Pydantic
Classifier: Intended Audience :: Developers
Classifier: Intended Audience :: Information Technology
Classifier: Intended Audience :: System Administrators
Classifier: License :: OSI Approved :: MIT License
Classifier: Operating System :: OS Independent
Classifier: Programming Language :: Python :: 3 :: Only
Classifier: Programming Language :: Python :: 3.10
Classifier: Programming Language :: Python :: 3.11
Classifier: Programming Language :: Python :: 3.7
Classifier: Programming Language :: Python :: 3.8
Classifier: Programming Language :: Python :: 3.9
Classifier: Programming Language :: Python :: 3
Classifier: Programming Language :: Python
Classifier: Topic :: Internet :: WWW/HTTP :: HTTP Servers
Classifier: Topic :: Internet :: WWW/HTTP
Classifier: Topic :: Internet
Classifier: Topic :: Software Development :: Libraries :: Application Frameworks
Classifier: Topic :: Software Development :: Libraries :: Python Modules
Classifier: Topic :: Software Development :: Libraries
Classifier: Topic :: Software Development
Classifier: Typing :: Typed
Requires-Python: >=3.8
License-File: LICENSE.txt
Requires-Dist: pydantic>=1.8
Requires-Dist: pytz>=2023.3
Requires-Dist: starlette>=0.24.0
Provides-Extra: oauth-token
Requires-Dist: pydantic>=1.8; extra == "oauth-token"
Requires-Dist: pytz>=2023.3; extra == "oauth-token"
Requires-Dist: starlette>=0.24.0; extra == "oauth-token"
Requires-Dist: fastapi>=0.96.0; extra == "oauth-token"
Requires-Dist: starlette>=0.24.0; extra == "oauth-token"
Requires-Dist: aiohttp>=3.8.5; extra == "oauth-token"
Requires-Dist: PyJWT>=2.7.0; extra == "oauth-token"
Provides-Extra: api-key-simple-auth
Requires-Dist: pydantic>=1.8; extra == "api-key-simple-auth"
Requires-Dist: pytz>=2023.3; extra == "api-key-simple-auth"
Requires-Dist: starlette>=0.24.0; extra == "api-key-simple-auth"
Requires-Dist: fastapi>=0.96.0; extra == "api-key-simple-auth"
Requires-Dist: starlette>=0.24.0; extra == "api-key-simple-auth"
Requires-Dist: aiohttp>=3.8.5; extra == "api-key-simple-auth"
Requires-Dist: PyJWT>=2.7.0; extra == "api-key-simple-auth"
Provides-Extra: oauth-token-api-key-simple-auth
Requires-Dist: pydantic>=1.8; extra == "oauth-token-api-key-simple-auth"
Requires-Dist: pytz>=2023.3; extra == "oauth-token-api-key-simple-auth"
Requires-Dist: starlette>=0.24.0; extra == "oauth-token-api-key-simple-auth"
Requires-Dist: fastapi>=0.96.0; extra == "oauth-token-api-key-simple-auth"
Requires-Dist: starlette>=0.24.0; extra == "oauth-token-api-key-simple-auth"
Requires-Dist: aiohttp>=3.8.5; extra == "oauth-token-api-key-simple-auth"
Requires-Dist: PyJWT>=2.7.0; extra == "oauth-token-api-key-simple-auth"
Requires-Dist: fastapi>=0.96.0; extra == "oauth-token-api-key-simple-auth"
Requires-Dist: starlette>=0.24.0; extra == "oauth-token-api-key-simple-auth"
Requires-Dist: aiohttp>=3.8.5; extra == "oauth-token-api-key-simple-auth"
Requires-Dist: PyJWT>=2.7.0; extra == "oauth-token-api-key-simple-auth"
